pylambdatasks/__init__.py
pylambdatasks/app.py
pylambdatasks/brokers.py
pylambdatasks/cli.py
pylambdatasks/config.py
pylambdatasks/dependencies.py
pylambdatasks/exceptions.py
pylambdatasks/logger.py
pylambdatasks/registry.py
pylambdatasks/server.py
pylambdatasks/task.py
pylambdatasks/utils.py
pylambdatasks-0.1.14.dist-info/licenses/LICENSE
pylambdatasks-0.1.14.dist-info/METADATA
pylambdatasks-0.1.14.dist-info/WHEEL
pylambdatasks-0.1.14.dist-info/entry_points.txt
pylambdatasks-0.1.14.dist-info/top_level.txt
pylambdatasks-0.1.14.dist-info/RECORD
