Metadata-Version: 2.4
Name: pylambdatasks
Version: 0.1.14
Summary: A library to simplify creating AWS Lambda images and managing multiple tasks within one image.
Author-email: Oktylab <contact@oktylab.com>, Crosspost <services@crosspost.app>
Maintainer-email: oktylab <contact@oktylab.com>, Crosspost <services@crosspost.app>
License-Expression: GPL-3.0-or-later
Project-URL: Homepage, https://github.com/oktylab/PyLambdaTasks
Project-URL: Repository, https://github.com/oktylab/PyLambdaTasks
Project-URL: Bug Tracker, https://github.com/oktylab/PyLambdaTasks/issues
Keywords: aws,lambda,serverless,tasks,async,boto3
Classifier: Development Status :: 3 - Alpha
Classifier: Intended Audience :: Developers
Classifier: Programming Language :: Python :: 3
Classifier: Programming Language :: Python :: 3.10
Classifier: Programming Language :: Python :: 3.11
Classifier: Programming Language :: Python :: 3.12
Classifier: Topic :: Software Development :: Libraries :: Python Modules
Classifier: Topic :: System :: Distributed Computing
Classifier: Operating System :: OS Independent
Requires-Python: >=3.10
License-File: LICENSE
Requires-Dist: boto3
Requires-Dist: awslambdaric
Provides-Extra: cli
Requires-Dist: typer; extra == "cli"
Requires-Dist: rich; extra == "cli"
Dynamic: license-file
